{
  "id": "B4705222-BFA5-4DCD-8811-A7A086A72DAD",
  "name": "GetArtifactFromUncShare",
  "friendlyName": "Get Artifact From UNC Share",
  "description": "Gets the contents of a remote TFS server build's drop location",
  "helpMarkDown": "Version: #{Build.BuildNumber}#. [More Information](https://github.com/rfennell/vNextBuild/wiki/File-Copier-Tasks/)",

  "category": "Utility",
  "visibility": [
                "Build",
                "Release"
                ],
  "author": "Black Marble",
  "version": {
    "Major": 1,
    "Minor": 0,
    "Patch": 0
  },
  "minimumAgentVersion": "1.82.0",
   "groups": [
    {
      "name": "advanced",
      "displayName": "Advanced",
      "isExpanded": false
    }
  ],
  
   "inputs": [
      {
         "name": "tfsUri",
         "type": "string",
         "label": "TFS Uri",
         "defaultValue": "",
         "required": true,
         "helpMarkDown": "The URI of the TFS server  e.g. http://myserver:8080/tfs/defaultcollection"
      },
      {
         "name": "teamproject",
         "type": "string",
         "label": "Team Project",
         "defaultValue": "",
         "required": true,
         "helpMarkDown": "The name of the source team project"
      }
      ,
      {
         "name": "defname",
         "type": "string",
         "label": "Build definition name",
         "defaultValue": "",
         "required": true,
         "helpMarkDown": "The name of the build definition."
      }
      ,
      {
         "name": "artifactname",
         "type": "string",
         "label": "Artifact name",
         "defaultValue": "",
         "required": true,
         "helpMarkDown": "The name of the build artifact."
      }
      ,
        {
      "name": "buildnumber",
      "type": "string",
      "label": "Specific build number",
      "defaultValue": "<Lastest Build>",
      "required": false,
      "helpMarkDown": "Number of the build to download (if blank latest complete build used)"
      }
      ,
      {
      "name": "username",
      "type": "string",
      "label": "Username",
      "defaultValue": "",
      "required": false,
      "helpMarkDown": "User name to access remote server (if blank default creds. used)",
      "groupName":"advanced"
      }
      ,
      {
      "name": "password",
      "type": "string",
      "label": "Password",
      "defaultValue": "",
      "required": false,
      "helpMarkDown": "Password to access remote server (if blank default creds. used)",
      "groupName":"advanced"
      }
      ,
      {
      "name": "localdir",
      "type": "string",
      "label": "Local Directory",
      "defaultValue": "$(SYSTEM.ARTIFACTSDIRECTORY)",
      "required": true,
      "helpMarkDown": "The root directory to store the artifact in, defaults to $(SYSTEM.ARTIFACTSDIRECTORY)",
      "groupName":"advanced"
      }
   ],
  "instanceNameFormat": "Get Artifact From UNC Share",
  "execution": {
    "PowerShell3": {
      "target": "$(currentDirectory)\\GetArtifactFromUncShare.ps1",
      "argumentFormat": "",
      "workingDirectory": "$(currentDirectory)"
    }
  }
}